MANIFEST.in
README.rst
README.txt
setup.py
bin/qtfaststart
qtfaststart/__init__.py
qtfaststart/__main__.py
qtfaststart/command.py
qtfaststart/exceptions.py
qtfaststart/processor.py
qtfaststart.egg-info/PKG-INFO
qtfaststart.egg-info/SOURCES.txt
qtfaststart.egg-info/dependency_links.txt
qtfaststart.egg-info/top_level.txt