Metadata-Version: 1.1
Name: qtfaststart
Version: 1.8
Summary: Quicktime atom positioning in Python for fast streaming.
Home-page: https://github.com/gtaylor/qtfaststart
Author: Daniel G. Taylor
Author-email: dan@programmer-art.org
License: MIT License
Platform: any
Classifier: Development Status :: 5 - Production/Stable
Classifier: Intended Audience :: Developers
Classifier: License :: OSI Approved :: MIT License
Classifier: Natural Language :: English
Classifier: Operating System :: OS Independent
Classifier: Programming Language :: Python
Classifier: Topic :: Multimedia :: Video :: Conversion
Classifier: Topic :: Software Development :: Libraries :: Python Modules
Provides: qtfaststart
